Workbook

Sheet Tổng quan
A1: Kết quả validation search (20261007 09:58)
A2: Model e5-large đa ngôn ngữ + BM25 + từ điển Việt-Anh. Bộ held-out, không dùng để chọn model hay viết từ điển.
A4: A. Tìm tài liệu trong kb (53 câu)
A5: Biến thể | B5: Số lượt | C5: Hit@1 | D5: Hit@5
A6: Tiếng Anh | B6: =COUNTIF('KB - chi tiết'!$C$5:$C$216,A6) | C6: =AVERAGEIF('KB - chi tiết'!$C$5:$C$216,A6,'KB - chi tiết'!$F$5:$F$216) | D6: =AVERAGEIF('KB - chi tiết'!$C$5:$C$216,A6,'KB - chi tiết'!$G$5:$G$216)
A7: Tiếng Việt có dấu | B7: =COUNTIF('KB - chi tiết'!$C$5:$C$216,A7) | C7: =AVERAGEIF('KB - chi tiết'!$C$5:$C$216,A7,'KB - chi tiết'!$F$5:$F$216) | D7: =AVERAGEIF('KB - chi tiết'!$C$5:$C$216,A7,'KB - chi tiết'!$G$5:$G$216)
A8: Không dấu | B8: =COUNTIF('KB - chi tiết'!$C$5:$C$216,A8) | C8: =AVERAGEIF('KB - chi tiết'!$C$5:$C$216,A8,'KB - chi tiết'!$F$5:$F$216) | D8: =AVERAGEIF('KB - chi tiết'!$C$5:$C$216,A8,'KB - chi tiết'!$G$5:$G$216)
A9: Kiểu chat | B9: =COUNTIF('KB - chi tiết'!$C$5:$C$216,A9) | C9: =AVERAGEIF('KB - chi tiết'!$C$5:$C$216,A9,'KB - chi tiết'!$F$5:$F$216) | D9: =AVERAGEIF('KB - chi tiết'!$C$5:$C$216,A9,'KB - chi tiết'!$G$5:$G$216)
A10: Tất cả | B10: =COUNTA('KB - chi tiết'!$C$5:$C$216) | C10: =AVERAGE('KB - chi tiết'!$F$5:$F$216) | D10: =AVERAGE('KB - chi tiết'!$G$5:$G$216)
A12: Hit@5 theo nhóm câu hỏi
A13: Nhóm | B13: Tiếng Anh | C13: Tiếng Việt có dấu | D13: Không dấu | E13: Kiểu chat
A14: Sản phẩm | B14: =AVERAGEIFS('KB - chi tiết'!$G$5:$G$216,'KB - chi tiết'!$B$5:$B$216,$A14,'KB - chi tiết'!$C$5:$C$216,B$13) | C14: =AVERAGEIFS('KB - chi tiết'!$G$5:$G$216,'KB - chi tiết'!$B$5:$B$216,$A14,'KB - chi tiết'!$C$5:$C$216,C$13) | D14: =AVERAGEIFS('KB - chi tiết'!$G$5:$G$216,'KB - chi tiết'!$B$5:$B$216,$A14,'KB - chi tiết'!$C$5:$C$216,D$13) | E14: =AVERAGEIFS('KB - chi tiết'!$G$5:$G$216,'KB - chi tiết'!$B$5:$B$216,$A14,'KB - chi tiết'!$C$5:$C$216,E$13)
A15: Insight | B15: =AVERAGEIFS('KB - chi tiết'!$G$5:$G$216,'KB - chi tiết'!$B$5:$B$216,$A15,'KB - chi tiết'!$C$5:$C$216,B$13) | C15: =AVERAGEIFS('KB - chi tiết'!$G$5:$G$216,'KB - chi tiết'!$B$5:$B$216,$A15,'KB - chi tiết'!$C$5:$C$216,C$13) | D15: =AVERAGEIFS('KB - chi tiết'!$G$5:$G$216,'KB - chi tiết'!$B$5:$B$216,$A15,'KB - chi tiết'!$C$5:$C$216,D$13) | E15: =AVERAGEIFS('KB - chi tiết'!$G$5:$G$216,'KB - chi tiết'!$B$5:$B$216,$A15,'KB - chi tiết'!$C$5:$C$216,E$13)
A16: Compliance | B16: =AVERAGEIFS('KB - chi tiết'!$G$5:$G$216,'KB - chi tiết'!$B$5:$B$216,$A16,'KB - chi tiết'!$C$5:$C$216,B$13) | C16: =AVERAGEIFS('KB - chi tiết'!$G$5:$G$216,'KB - chi tiết'!$B$5:$B$216,$A16,'KB - chi tiết'!$C$5:$C$216,C$13) | D16: =AVERAGEIFS('KB - chi tiết'!$G$5:$G$216,'KB - chi tiết'!$B$5:$B$216,$A16,'KB - chi tiết'!$C$5:$C$216,D$13) | E16: =AVERAGEIFS('KB - chi tiết'!$G$5:$G$216,'KB - chi tiết'!$B$5:$B$216,$A16,'KB - chi tiết'!$C$5:$C$216,E$13)
A17: SOP | B17: =AVERAGEIFS('KB - chi tiết'!$G$5:$G$216,'KB - chi tiết'!$B$5:$B$216,$A17,'KB - chi tiết'!$C$5:$C$216,B$13) | C17: =AVERAGEIFS('KB - chi tiết'!$G$5:$G$216,'KB - chi tiết'!$B$5:$B$216,$A17,'KB - chi tiết'!$C$5:$C$216,C$13) | D17: =AVERAGEIFS('KB - chi tiết'!$G$5:$G$216,'KB - chi tiết'!$B$5:$B$216,$A17,'KB - chi tiết'!$C$5:$C$216,D$13) | E17: =AVERAGEIFS('KB - chi tiết'!$G$5:$G$216,'KB - chi tiết'!$B$5:$B$216,$A17,'KB - chi tiết'!$C$5:$C$216,E$13)
A18: Chính sách | B18: =AVERAGEIFS('KB - chi tiết'!$G$5:$G$216,'KB - chi tiết'!$B$5:$B$216,$A18,'KB - chi tiết'!$C$5:$C$216,B$13) | C18: =AVERAGEIFS('KB - chi tiết'!$G$5:$G$216,'KB - chi tiết'!$B$5:$B$216,$A18,'KB - chi tiết'!$C$5:$C$216,C$13) | D18: =AVERAGEIFS('KB - chi tiết'!$G$5:$G$216,'KB - chi tiết'!$B$5:$B$216,$A18,'KB - chi tiết'!$C$5:$C$216,D$13) | E18: =AVERAGEIFS('KB - chi tiết'!$G$5:$G$216,'KB - chi tiết'!$B$5:$B$216,$A18,'KB - chi tiết'!$C$5:$C$216,E$13)
A19: Creative | B19: =AVERAGEIFS('KB - chi tiết'!$G$5:$G$216,'KB - chi tiết'!$B$5:$B$216,$A19,'KB - chi tiết'!$C$5:$C$216,B$13) | C19: =AVERAGEIFS('KB - chi tiết'!$G$5:$G$216,'KB - chi tiết'!$B$5:$B$216,$A19,'KB - chi tiết'!$C$5:$C$216,C$13) | D19: =AVERAGEIFS('KB - chi tiết'!$G$5:$G$216,'KB - chi tiết'!$B$5:$B$216,$A19,'KB - chi tiết'!$C$5:$C$216,D$13) | E19: =AVERAGEIFS('KB - chi tiết'!$G$5:$G$216,'KB - chi tiết'!$B$5:$B$216,$A19,'KB - chi tiết'!$C$5:$C$216,E$13)
A20: Brand | B20: =AVERAGEIFS('KB - chi tiết'!$G$5:$G$216,'KB - chi tiết'!$B$5:$B$216,$A20,'KB - chi tiết'!$C$5:$C$216,B$13) | C20: =AVERAGEIFS('KB - chi tiết'!$G$5:$G$216,'KB - chi tiết'!$B$5:$B$216,$A20,'KB - chi tiết'!$C$5:$C$216,C$13) | D20: =AVERAGEIFS('KB - chi tiết'!$G$5:$G$216,'KB - chi tiết'!$B$5:$B$216,$A20,'KB - chi tiết'!$C$5:$C$216,D$13) | E20: =AVERAGEIFS('KB - chi tiết'!$G$5:$G$216,'KB - chi tiết'!$B$5:$B$216,$A20,'KB - chi tiết'!$C$5:$C$216,E$13)
A21: Khoảng trống dữ liệu | B21: =AVERAGEIFS('KB - chi tiết'!$G$5:$G$216,'KB - chi tiết'!$B$5:$B$216,$A21,'KB - chi tiết'!$C$5:$C$216,B$13) | C21: =AVERAGEIFS('KB - chi tiết'!$G$5:$G$216,'KB - chi tiết'!$B$5:$B$216,$A21,'KB - chi tiết'!$C$5:$C$216,C$13) | D21: =AVERAGEIFS('KB - chi tiết'!$G$5:$G$216,'KB - chi tiết'!$B$5:$B$216,$A21,'KB - chi tiết'!$C$5:$C$216,D$13) | E21: =AVERAGEIFS('KB - chi tiết'!$G$5:$G$216,'KB - chi tiết'!$B$5:$B$216,$A21,'KB - chi tiết'!$C$5:$C$216,E$13)
A23: B. Tìm review có bộ lọc (15 câu)
A24: Biến thể | B24: Số câu | C24: Precision@5 | D24: Vi phạm bộ lọc
A25: Tiếng Anh | B25: =COUNTIF(Review!$B$5:$B$49,A25) | C25: =AVERAGEIF(Review!$B$5:$B$49,A25,Review!$G$5:$G$49) | D25: =SUMIF(Review!$B$5:$B$49,A25,Review!$H$5:$H$49)
A26: Tiếng Việt có dấu | B26: =COUNTIF(Review!$B$5:$B$49,A26) | C26: =AVERAGEIF(Review!$B$5:$B$49,A26,Review!$G$5:$G$49) | D26: =SUMIF(Review!$B$5:$B$49,A26,Review!$H$5:$H$49)
A27: Không dấu | B27: =COUNTIF(Review!$B$5:$B$49,A27) | C27: =AVERAGEIF(Review!$B$5:$B$49,A27,Review!$G$5:$G$49) | D27: =SUMIF(Review!$B$5:$B$49,A27,Review!$H$5:$H$49)
A29: C. Câu hỏi ngoài phạm vi (12 câu x 2 ngôn ngữ)
A30: Ngưỡng cosine đang dùng | C30: ='Ngoài phạm vi'!C4
A31: Tỉ lệ câu ngoài phạm vi bị loại | C31: ='Ngoài phạm vi'!C5
A32: Điểm cao nhất của câu ngoài phạm vi | C32: =MAX('Ngoài phạm vi'!E8:E31)
A33: Trung vị điểm câu hợp lệ | C33: ='Ngoài phạm vi'!C35
A35: Màu: xanh ≥ 85%, vàng 70-85%, đỏ < 70%. Chữ xanh lá = liên kết sang sheet khác.

Sheet KB - chi tiết
A1: Tìm tài liệu trong kb: từng lượt chạy
A2: Hạng = vị trí của chunk đúng đầu tiên trong top 10 (trống = không tìm thấy). Top 5 = 1 nếu hạng ≤ 5.
A4: ID | B4: Nhóm | C4: Biến thể | D4: Câu hỏi | E4: Hạng | F4: Top 1 | G4: Top 5 | H4: Đáp án mong đợi | I4: Kết quả 1 | J4: Kết quả 2 | K4: Kết quả 3
A5: V01 | B5: Sản phẩm | C5: Tiếng Anh | D5: What is the price of the Avocado barrier serum? | E5: 1 | F5: =IF(E5=1,1,0) | G5: =IF(AND(E5<>"",E5<=5),1,0) | H5: product/P470529#overview | I5: product/P470529#overview | J5: catalog/overview#avocado-line | K5: research/insights-P470529#by-year
A6: V01 | B6: Sản phẩm | C6: Tiếng Việt có dấu | D6: Serum Avocado phục hồi hàng rào da giá bao nhiêu? | E6: 1 | F6: =IF(E6=1,1,0) | G6: =IF(AND(E6<>"",E6<=5),1,0) | H6: product/P470529#overview | I6: product/P470529#overview | J6: catalog/overview#avocado-line | K6: policy/shipping#what-the-page-does-not-state
A7: V01 | B7: Sản phẩm | C7: Không dấu | D7: Serum Avocado phuc hoi hang rao da gia bao nhieu? | E7: 2 | F7: =IF(E7=1,1,0) | G7: =IF(AND(E7<>"",E7<=5),1,0) | H7: product/P470529#overview | I7: catalog/overview#avocado-line | J7: product/P470529#overview | K7: creative/learnings-2023#ct-09
A8: V01 | B8: Sản phẩm | C8: Kiểu chat | D8: serum bo phuc hoi bn tien v | E8: 5 | F8: =IF(E8=1,1,0) | G8: =IF(AND(E8<>"",E8<=5),1,0) | H8: product/P470529#overview | I8: catalog/overview#avocado-line | J8: catalog/overview#strawberry-line | K8: product/P482535#ingredients
A9: V02 | B9: Sản phẩm | C9: Tiếng Anh | D9: Does the Guava eye cream contain vitamin C? | E9: 2 | F9: =IF(E9=1,1,0) | G9: =IF(AND(E9<>"",E9<=5),1,0) | H9: product/P501760 | I9: catalog/overview#guava-line | J9: product/P501760#overview | K9: research/insights-line-guava#products-in-this-line
A10: V02 | B10: Sản phẩm | C10: Tiếng Việt có dấu | D10: Kem mắt Guava có vitamin C không? | E10: 2 | F10: =IF(E10=1,1,0) | G10: =IF(AND(E10<>"",E10<=5),1,0) | H10: product/P501760 | I10: research/insights-line-guava#products-in-this-line | J10: product/P501760#overview | K10: catalog/overview#guava-line
A11: V02 | B11: Sản phẩm | C11: Không dấu | D11: Kem mat Guava co vitamin C khong? | E11: 1 | F11: =IF(E11=1,1,0) | G11: =IF(AND(E11<>"",E11<=5),1,0) | H11: product/P501760 | I11: product/P501760#overview | J11: catalog/overview#guava-line | K11: research/insights-line-guava#products-in-this-line
A12: V02 | B12: Sản phẩm | C12: Kiểu chat | D12: kem mat oi co vit C hok | E12: 1 | F12: =IF(E12=1,1,0) | G12: =IF(AND(E12<>"",E12<=5),1,0) | H12: product/P501760 | I12: product/P501760#overview | J12: catalog/overview#guava-line | K12: research/insights-line-guava#products-in-this-line
A13: V03 | B13: Sản phẩm | C13: Tiếng Anh | D13: What size is the Watermelon Glow facial mist? | E13: 1 | F13: =IF(E13=1,1,0) | G13: =IF(AND(E13<>"",E13<=5),1,0) | H13: product/P442744#overview | I13: product/P442744#overview | J13: catalog/overview#watermelon-line | K13: product/P467762#overview
A14: V03 | B14: Sản phẩm | C14: Tiếng Việt có dấu | D14: Xịt khoáng Watermelon Glow dung tích bao nhiêu? | E14: 1 | F14: =IF(E14=1,1,0) | G14: =IF(AND(E14<>"",E14<=5),1,0) | H14: product/P442744#overview | I14: product/P442744#overview | J14: research/insights-line-watermelon#products-in-this-line | K14: product/P467762#overview
A15: V03 | B15: Sản phẩm | C15: Không dấu | D15: Xit khoang Watermelon Glow dung tich bao nhieu? | E15: 2 | F15: =IF(E15=1,1,0) | G15: =IF(AND(E15<>"",E15<=5),1,0) | H15: product/P442744#overview | I15: research/insights-line-watermelon#products-in-this-line | J15: product/P442744#overview | K15: product/P467762#overview
A16: V03 | B16: Sản phẩm | C16: Kiểu chat | D16: xit khoang dua hau bao nhieu ml | E16: 2 | F16: =IF(E16=1,1,0) | G16: =IF(AND(E16<>"",E16<=5),1,0) | H16: product/P442744#overview | I16: catalog/overview#products-sold-in-more-than-one-size | J16: product/P442744#overview | K16: catalog/overview#watermelon-line
... A35: V08 | B35: Insight | C35: Không dấu | D35: Khach thich dieu gi nhat o serum Plum Plump? | E35: 6 | F35: =IF(E35=1,1,0) | G35: =IF(AND(E35<>"",E35<=5),1,0) | H35: research/insights-P462699 | I35: product/P462699#overview | J35: catalog/overview#plum-line | K35: product/P462699#ingredients
A36: V08 | B36: Insight | C36: Kiểu chat | D36: serum man dc khen gi nhieu nhat | F36: =IF(E36=1,1,0) | G36: =IF(AND(E36<>"",E36<=5),1,0) | H36: research/insights-P462699 | I36: research/insights-P475543#themes | J36: catalog/overview#strawberry-line | K36: product/P479327#overview
A37: V09 | B37: Insight | C37: Tiếng Anh | D37: Is the retinol eye cream irritating according to reviews? | E37: 1 | F37: =IF(E37=1,1,0) | G37: =IF(AND(E37<>"",E37<=5),1,0) | H37: research/insights-P447791 | I37: research/insights-P447791#evidence-by-theme-2 | J37: research/insights-P447791#how-to-read-this | K37: brand/claims-policy#cp-08
A38: V09 | B38: Insight | C38: Tiếng Việt có dấu | D38: Theo review, kem mắt retinol có gây kích ứng không? | E38: 1 | F38: =IF(E38=1,1,0) | G38: =IF(AND(E38<>"",E38<=5),1,0) | H38: research/insights-P447791 | I38: research/insights-P447791#how-to-read-this | J38: research/insights-P501760#evidence-by-theme-2 | K38: product/P447791#overview
A39: V09 | B39: Insight | C39: Không dấu | D39: Theo review, kem mat retinol co gay kich ung khong? | E39: 1 | F39: =IF(E39=1,1,0) | G39: =IF(AND(E39<>"",E39<=5),1,0) | H39: research/insights-P447791 | I39: research/insights-P447791#how-to-read-this | J39: research/insights-P501760#how-to-read-this | K39: research/insights-P501760#evidence-by-theme-2
A40: V09 | B40: Insight | C40: Kiểu chat | D40: kem mat retinol co bi kich ung ko | E40: 2 | F40: =IF(E40=1,1,0) | G40: =IF(AND(E40<>"",E40<=5),1,0) | H40: research/insights-P447791 | I40: brand/claims-policy#cp-08 | J40: research/insights-P447791#how-to-read-this | K40: research/insights-P501760#evidence-by-theme-2
A41: V10 | B41: Insight | C41: Tiếng Anh | D41: How has the Blueberry cleanser rating changed over the years? | E41: 1 | F41: =IF(E41=1,1,0) | G41: =IF(AND(E41<>"",E41<=5),1,0) | H41: research/insights-P436359#by-year | I41: research/insights-P436359#by-year | J41: creative/learnings-2023#recommended-next-tests-as-of-2023-04 | K41: research/insights-P436359#overview
A42: V10 | B42: Insight | C42: Tiếng Việt có dấu | D42: Đánh giá sữa rửa mặt Blueberry thay đổi thế nào qua các năm? | F42: =IF(E42=1,1,0) | G42: =IF(AND(E42<>"",E42<=5),1,0) | H42: research/insights-P436359#by-year | I42: product/P436359#overview | J42: research/insights-line-blueberry#products-in-this-line | K42: catalog/overview#blueberry-line
A43: V10 | B43: Insight | C43: Không dấu | D43: Danh gia sua rua mat Blueberry thay doi the nao qua cac nam? | F43: =IF(E43=1,1,0) | G43: =IF(AND(E43<>"",E43<=5),1,0) | H43: research/insights-P436359#by-year | I43: research/insights-line-blueberry#products-in-this-line | J43: research/insights-line-blueberry#themes | K43: brand/claims-policy#cp-03
A44: V10 | B44: Insight | C44: Kiểu chat | D44: srm viet quat rating qua tung nam sao roi | E44: 4 | F44: =IF(E44=1,1,0) | G44: =IF(AND(E44<>"",E44<=5),1,0) | H44: research/insights-P436359#by-year | I44: creative/learnings-2023#recommended-next-tests-as-of-2023-04 | J44: research/insights-overview#by-year | K44: brand/claims-policy#cp-03
A45: V11 | B45: Insight | C45: Tiếng Anh | D45: Which skin type rates the Dew Drops the highest? | E45: 1 | F45: =IF(E45=1,1,0) | G45: =IF(AND(E45<>"",E45<=5),1,0) | H45: research/insights-P466123#by-skin-type | I45: research/insights-P466123#by-skin-type | J45: research/insights-P504125#by-skin-type | K45: research/insights-P466123#themes
A46: V11 | B46: Insight | C46: Tiếng Việt có dấu | D46: Loại da nào chấm Dew Drops cao nhất? | E46: 4 | F46: =IF(E46=1,1,0) | G46: =IF(AND(E46<>"",E46<=5),1,0) | H46: research/insights-P466123#by-skin-type | I46: research/insights-P466123#themes | J46: brand/brand-overview#positioning | K46: catalog/overview#products-by-price
A47: V11 | B47: Insight | C47: Không dấu | D47: Loai da nao cham Dew Drops cao nhat? | F47: =IF(E47=1,1,0) | G47: =IF(AND(E47<>"",E47<=5),1,0) | H47: research/insights-P466123#by-skin-type | I47: creative/learnings-2023#ct-01 | J47: brand/voice-guide#examples | K47: brand/brand-overview#positioning
A48: V11 | B48: Insight | C48: Kiểu chat | D48: da nao cham dew drops cao nhat | F48: =IF(E48=1,1,0) | G48: =IF(AND(E48<>"",E48<=5),1,0) | H48: research/insights-P466123#by-skin-type | I48: creative/learnings-2023#ct-02 | J48: catalog/overview#products-by-price | K48: brand/brand-overview#positioning
A49: V12 | B49: Insight | C49: Tiếng Anh | D49: Do customers find the Watermelon Pink Juice moisturizer sticky? | E49: 1 | F49: =IF(E49=1,1,0) | G49: =IF(AND(E49<>"",E49<=5),1,0) | H49: research/insights-P428819 | I49: research/insights-P428819#evidence-by-theme | J49: product/P428819#overview | K49: research/insights-P428819#overview
A50: V12 | B50: Insight | C50: Tiếng Việt có dấu | D50: Khách có thấy kem dưỡng Watermelon Pink Juice bị dính không? | E50: 2 | F50: =IF(E50=1,1,0) | G50: =IF(AND(E50<>"",E50<=5),1,0) | H50: research/insights-P428819 | I50: catalog/overview#products-by-price | J50: research/insights-P428819#evidence-by-theme | K50: research/insights-P428819#overview
A51: V12 | B51: Insight | C51: Không dấu | D51: Khach co thay kem duong Watermelon Pink Juice bi dinh khong? | E51: 5 | F51: =IF(E51=1,1,0) | G51: =IF(AND(E51<>"",E51<=5),1,0) | H51: research/insights-P428819 | I51: catalog/overview#products-by-price | J51: product/P428819#overview | K51: research/insights-line-guava#evidence-by-theme-2
A52: V12 | B52: Insight | C52: Kiểu chat | D52: kem duong dua hau pink juice co bi dinh ko | E52: 1 | F52: =IF(E52=1,1,0) | G52: =IF(AND(E52<>"",E52<=5),1,0) | H52: research/insights-P428819 | I52: research/insights-P428819#evidence-by-theme | J52: sop/review-response#usage-tips-by-complaint-theme | K52: catalog/overview#products-by-price
A53: V13 | B53: Insight | C53: Tiếng Anh | D53: Which product line has the most reviews? | E53: 5 | F53: =IF(E53=1,1,0) | G53: =IF(AND(E53<>"",E53<=5),1,0) | H53: research/insights-overview#by-product-line | I53: catalog/overview#catalog-summary | J53: research/insights-line-strawberry#themes | K53: catalog/overview#avocado-line
A54: V13 | B54: Insight | C54: Tiếng Việt có dấu | D54: Dòng sản phẩm nào có nhiều review nhất? | F54: =IF(E54=1,1,0) | G54: =IF(AND(E54<>"",E54<=5),1,0) | H54: research/insights-overview#by-product-line | I54: research/insights-line-strawberry#themes | J54: compliance/ftc-endorsement-guides#reviews | K54: research/insights-line-watermelon#themes
A55: V13 | B55: Insight | C55: Không dấu | D55: Dong san pham nao co nhieu review nhat? | F55: =IF(E55=1,1,0) | G55: =IF(AND(E55<>"",E55<=5),1,0) | H55: research/insights-overview#by-product-line | I55: sop/influencer-brief#product-specific-notes-from-customer-research | J55: compliance/ftc-endorsement-guides#reviews | K55: sop/review-response#principles
A56: V13 | B56: Insight | C56: Kiểu chat | D56: dong nao nhieu review nhat | F56: =IF(E56=1,1,0) | G56: =IF(AND(E56<>"",E56<=5),1,0) | H56: research/insights-overview#by-product-line | I56: compliance/ftc-endorsement-guides#reviews | J56: sop/influencer-brief#product-specific-notes-from-customer-research | K56: compliance/ftc-health-claims#practical-implications-knowledge-base-s-reading
A57: V14 | B57: Insight | C57: Tiếng Anh | D57: What share of reviews came from people who got the product for free? | F57: =IF(E57=1,1,0) | G57: =IF(AND(E57<>"",E57<=5),1,0) | H57: research/insights-overview#overview | I57: research/insights-P428819#how-to-read-this | J57: brand/voice-guide#talking-about-scent | K57: research/insights-P504125#how-to-read-this
A58: V14 | B58: Insight | C58: Tiếng Việt có dấu | D58: Bao nhiêu phần trăm review là từ người được tặng sản phẩm? | F58: =IF(E58=1,1,0) | G58: =IF(AND(E58<>"",E58<=5),1,0) | H58: research/insights-overview#overview | I58: compliance/ftc-endorsement-guides#reviews | J58: sop/influencer-brief#when-to-use | K58: research/insights-line-strawberry#overview
A59: V14 | B59: Insight | C59: Không dấu | D59: Bao nhieu phan tram review la tu nguoi duoc tang san pham? | F59: =IF(E59=1,1,0) | G59: =IF(AND(E59<>"",E59<=5),1,0) | H59: research/insights-overview#overview | I59: compliance/ftc-endorsement-guides#reviews | J59: sop/influencer-brief#product-specific-notes-from-customer-research | K59: sop/influencer-brief#when-to-use
A60: V14 | B60: Insight | C60: Kiểu chat | D60: bao nhieu % review la do dc tang sp | F60: =IF(E60=1,1,0) | G60: =IF(AND(E60<>"",E60<=5),1,0) | H60: research/insights-overview#overview | I60: sop/ad-claim-review#self-check-checklist | J60: sop/influencer-brief#when-to-use | K60: compliance/ftc-endorsement-guides#reviews
A61: V15 | B61: Insight | C61: Tiếng Anh | D61: How do customers rate the Papaya cleansing balm? | E61: 2 | F61: =IF(E61=1,1,0) | G61: =IF(AND(E61<>"",E61<=5),1,0) | H61: research/insights-P460516 | I61: research/insights-line-papaya#products-in-this-line | J61: research/insights-P460516#overview | K61: research/insights-P460516#by-year
A62: V15 | B62: Insight | C62: Tiếng Việt có dấu | D62: Sáp tẩy trang Papaya được đánh giá thế nào? | E62: 1 | F62: =IF(E62=1,1,0) | G62: =IF(AND(E62<>"",E62<=5),1,0) | H62: research/insights-P460516 | I62: research/insights-P460516#by-year | J62: research/insights-line-papaya#products-in-this-line | K62: product/P460516#ingredients
A63: V15 | B63: Insight | C63: Không dấu | D63: Sap tay trang Papaya duoc danh gia the nao? | E63: 2 | F63: =IF(E63=1,1,0) | G63: =IF(AND(E63<>"",E63<=5),1,0) | H63: research/insights-P460516 | I63: catalog/overview#papaya-line | J63: research/insights-P460516#by-year | K63: product/P460516#ingredients
A64: V15 | B64: Insight | C64: Kiểu chat | D64: sap tay trang du du review sao | E64: 9 | F64: =IF(E64=1,1,0) | G64: =IF(AND(E64<>"",E64<=5),1,0) | H64: research/insights-P460516 | I64: sop/influencer-brief#product-specific-notes-from-customer-research | J64: catalog/overview#papaya-line | K64: compliance/ftc-endorsement-guides#reviews
A65: V16 | B65: Insight | C65: Tiếng Anh | D65: What do customers say about the Avocado line overall? | E65: 1 | F65: =IF(E65=1,1,0) | G65: =IF(AND(E65<>"",E65<=5),1,0) | H65: research/insights-line-avocado | I65: research/insights-line-avocado#overview | J65: brand/claims-policy#cp-08 | K65: research/insights-line-avocado#products-in-this-line
A66: V16 | B66: Insight | C66: Tiếng Việt có dấu | D66: Nhìn chung khách nói gì về dòng Avocado? | E66: 2 | F66: =IF(E66=1,1,0) | G66: =IF(AND(E66<>"",E66<=5),1,0) | H66: research/insights-line-avocado | I66: catalog/overview#avocado-line | J66: research/insights-line-avocado#themes | K66: research/insights-line-avocado#products-in-this-line
A67: V16 | B67: Insight | C67: Không dấu | D67: Nhin chung khach noi gi ve dong Avocado? | E67: 2 | F67: =IF(E67=1,1,0) | G67: =IF(AND(E67<>"",E67<=5),1,0) | H67: research/insights-line-avocado | I67: catalog/overview#avocado-line | J67: research/insights-line-avocado#evidence-by-theme-2 | K67: research/insights-line-avocado#products-in-this-line
A68: V16 | B68: Insight | C68: Kiểu chat | D68: dong bo khach noi gi | E68: 4 | F68: =IF(E68=1,1,0) | G68: =IF(AND(E68<>"",E68<=5),1,0) | H68: research/insights-line-avocado | I68: creative/brief-template#overview | J68: catalog/overview#avocado-line | K68: sop/influencer-brief#product-specific-notes-from-customer-research
A69: V17 | B69: Insight | C69: Tiếng Anh | D69: According to reviews, does the Guava serum help with dark spots? | E69: 2 | F69: =IF(E69=1,1,0) | G69: =IF(AND(E69<>"",E69<=5),1,0) | H69: research/insights-P475543 | I69: product/P475543#overview | J69: research/insights-P475543#evidence-by-theme-1 | K69: research/insights-P475543#by-year
A70: V17 | B70: Insight | C70: Tiếng Việt có dấu | D70: Theo review, serum Guava có giúp mờ thâm không? | E70: 1 | F70: =IF(E70=1,1,0) | G70: =IF(AND(E70<>"",E70<=5),1,0) | H70: research/insights-P475543 | I70: research/insights-P475543#evidence-by-theme-1 | J70: product/P475543#overview | K70: catalog/overview#guava-line
A71: V17 | B71: Insight | C71: Không dấu | D71: Theo review, serum Guava co giup mo tham khong? | E71: 1 | F71: =IF(E71=1,1,0) | G71: =IF(AND(E71<>"",E71<=5),1,0) | H71: research/insights-P475543 | I71: research/insights-P475543#evidence-by-theme-1 | J71: research/insights-P475543#evidence-by-theme-2 | K71: catalog/overview#guava-line
A72: V17 | B72: Insight | C72: Kiểu chat | D72: serum oi tri tham co hieu qua ko | E72: 4 | F72: =IF(E72=1,1,0) | G72: =IF(AND(E72<>"",E72<=5),1,0) | H72: research/insights-P475543 | I72: catalog/overview#guava-line | J72: research/insights-P504125#evidence-by-theme-1 | K72: creative/learnings-2023#ct-06
... A77: V19 | B77: Compliance | C77: Tiếng Anh | D77: Can we say the Avocado serum repairs the skin barrier? | E77: 4 | F77: =IF(E77=1,1,0) | G77: =IF(AND(E77<>"",E77<=5),1,0) | H77: brand/claims-policy#cp-01 | I77: product/P470529#overview | J77: brand/claims-policy#quick-lookup-by-product | K77: research/insights-P470529#by-year
A78: V19 | B78: Compliance | C78: Tiếng Việt có dấu | D78: Có được nói serum Avocado phục hồi hàng rào bảo vệ da không? | F78: =IF(E78=1,1,0) | G78: =IF(AND(E78<>"",E78<=5),1,0) | H78: brand/claims-policy#cp-01 | I78: product/P470529#overview | J78: catalog/overview#avocado-line | K78: research/insights-P470529#themes
A79: V19 | B79: Compliance | C79: Không dấu | D79: Co duoc noi serum Avocado phuc hoi hang rao bao ve da khong? | F79: =IF(E79=1,1,0) | G79: =IF(AND(E79<>"",E79<=5),1,0) | H79: brand/claims-policy#cp-01 | I79: product/P470529#overview | J79: creative/learnings-2023#ct-09 | K79: catalog/overview#avocado-line
A80: V19 | B80: Compliance | C80: Kiểu chat | D80: dc ghi serum bo phuc hoi hang rao da ko | F80: =IF(E80=1,1,0) | G80: =IF(AND(E80<>"",E80<=5),1,0) | H80: brand/claims-policy#cp-01 | I80: catalog/overview#avocado-line | J80: creative/learnings-2023#ct-06 | K80: catalog/overview#strawberry-line
A81: V20 | B81: Compliance | C81: Tiếng Anh | D81: Can we say the Guava serum fades melasma? | E81: 1 | F81: =IF(E81=1,1,0) | G81: =IF(AND(E81<>"",E81<=5),1,0) | H81: brand/claims-policy#cp-03 | I81: brand/claims-policy#cp-03 | J81: research/insights-P475543#evidence-by-theme-2 | K81: product/P475543#overview
A82: V20 | B82: Compliance | C82: Tiếng Việt có dấu | D82: Có được nói serum Guava làm mờ nám không? | E82: 4 | F82: =IF(E82=1,1,0) | G82: =IF(AND(E82<>"",E82<=5),1,0) | H82: brand/claims-policy#cp-03 | I82: product/P475543#overview | J82: research/insights-P475543#evidence-by-theme-1 | K82: catalog/overview#guava-line
A83: V20 | B83: Compliance | C83: Không dấu | D83: Co duoc noi serum Guava lam mo nam khong? | E83: 4 | F83: =IF(E83=1,1,0) | G83: =IF(AND(E83<>"",E83<=5),1,0) | H83: brand/claims-policy#cp-03 | I83: product/P475543#overview | J83: research/insights-P475543#evidence-by-theme-1 | K83: catalog/overview#guava-line
A84: V20 | B84: Compliance | C84: Kiểu chat | D84: ghi serum oi tri nam dc ko | E84: 2 | F84: =IF(E84=1,1,0) | G84: =IF(AND(E84<>"",E84<=5),1,0) | H84: brand/claims-policy#cp-03 | I84: product/P504636#overview | J84: brand/claims-policy#cp-03 | K84: research/insights-P504125#evidence-by-theme-1
A85: V21 | B85: Compliance | C85: Tiếng Anh | D85: Can we call our sunscreen a sunblock? | E85: 1 | F85: =IF(E85=1,1,0) | G85: =IF(AND(E85<>"",E85<=5),1,0) | H85: brand/claims-policy#cp-05 compliance/fda-sunscreen-labeling#prohibited-terms | I85: compliance/fda-sunscreen-labeling#prohibited-terms | J85: brand/claims-policy#cp-05 | K85: compliance/fda-sunscreen-labeling#overview
A86: V21 | B86: Compliance | C86: Tiếng Việt có dấu | D86: Có được gọi kem chống nắng là sunblock không? | E86: 1 | F86: =IF(E86=1,1,0) | G86: =IF(AND(E86<>"",E86<=5),1,0) | H86: brand/claims-policy#cp-05 compliance/fda-sunscreen-labeling#prohibited-terms | I86: compliance/fda-sunscreen-labeling#prohibited-terms | J86: brand/claims-policy#cp-05 | K86: product/P481989#overview
A87: V21 | B87: Compliance | C87: Không dấu | D87: Co duoc goi kem chong nang la sunblock khong? | E87: 1 | F87: =IF(E87=1,1,0) | G87: =IF(AND(E87<>"",E87<=5),1,0) | H87: brand/claims-policy#cp-05 compliance/fda-sunscreen-labeling#prohibited-terms | I87: brand/claims-policy#cp-05 | J87: compliance/fda-sunscreen-labeling#prohibited-terms | K87: compliance/fda-sunscreen-labeling#relevance
A88: V21 | B88: Compliance | C88: Kiểu chat | D88: ghi sunblock dc ko | E88: 1 | F88: =IF(E88=1,1,0) | G88: =IF(AND(E88<>"",E88<=5),1,0) | H88: brand/claims-policy#cp-05 compliance/fda-sunscreen-labeling#prohibited-terms | I88: brand/claims-policy#cp-05 | J88: compliance/fda-sunscreen-labeling#prohibited-terms | K88: brand/claims-policy#cp-04
A89: V22 | B89: Compliance | C89: Tiếng Anh | D89: How often must sunscreen copy tell people to reapply? | E89: 1 | F89: =IF(E89=1,1,0) | G89: =IF(AND(E89<>"",E89<=5),1,0) | H89: brand/claims-policy#cp-05 compliance/fda-sunscreen-labeling#water-resistance | I89: compliance/fda-sunscreen-labeling#water-resistance | J89: brand/claims-policy#cp-05 | K89: sop/ad-claim-review#self-check-checklist
A90: V22 | B90: Compliance | C90: Tiếng Việt có dấu | D90: Nội dung về kem chống nắng phải nhắc thoa lại sau bao lâu? | E90: 1 | F90: =IF(E90=1,1,0) | G90: =IF(AND(E90<>"",E90<=5),1,0) | H90: brand/claims-policy#cp-05 compliance/fda-sunscreen-labeling#water-resistance | I90: brand/claims-policy#cp-05 | J90: product/P481989#overview | K90: creative/learnings-2023#ct-04
A91: V22 | B91: Compliance | C91: Không dấu | D91: Noi dung ve kem chong nang phai nhac thoa lai sau bao lau? | E91: 8 | F91: =IF(E91=1,1,0) | G91: =IF(AND(E91<>"",E91<=5),1,0) | H91: brand/claims-policy#cp-05 compliance/fda-sunscreen-labeling#water-resistance | I91: sop/influencer-brief#product-specific-notes-from-customer-research | J91: product/P481989#overview | K91: compliance/fda-sunscreen-labeling#relevance
A92: V22 | B92: Compliance | C92: Kiểu chat | D92: kem chong nang phai ghi thoa lai bao lau | E92: 8 | F92: =IF(E92=1,1,0) | G92: =IF(AND(E92<>"",E92<=5),1,0) | H92: brand/claims-policy#cp-05 compliance/fda-sunscreen-labeling#water-resistance | I92: sop/influencer-brief#product-specific-notes-from-customer-research | J92: product/P481989#overview | K92: sop/review-response#reply-templates
... A101: V25 | B101: Compliance | C101: Tiếng Anh | D101: Is it fine to call it our best-selling serum? | E101: 5 | F101: =IF(E101=1,1,0) | G101: =IF(AND(E101<>"",E101<=5),1,0) | H101: brand/claims-policy#cp-12 | I101: sop/ad-claim-review#claims-register-status-as-of-2023-04-01 | J101: creative/learnings-2023#ct-09 | K101: research/insights-P475543#evidence-by-theme-1
A102: V25 | B102: Compliance | C102: Tiếng Việt có dấu | D102: Có được nói đây là serum bán chạy nhất không? | F102: =IF(E102=1,1,0) | G102: =IF(AND(E102<>"",E102<=5),1,0) | H102: brand/claims-policy#cp-12 | I102: research/insights-line-plum#evidence-by-theme-1 | J102: catalog/overview#strawberry-line | K102: research/insights-P475543#evidence-by-theme-1
A103: V25 | B103: Compliance | C103: Không dấu | D103: Co duoc noi day la serum ban chay nhat khong? | F103: =IF(E103=1,1,0) | G103: =IF(AND(E103<>"",E103<=5),1,0) | H103: brand/claims-policy#cp-12 | I103: creative/learnings-2023#ct-04 | J103: creative/learnings-2023#ct-06 | K103: brand/voice-guide#vocabulary
A104: V25 | B104: Compliance | C104: Kiểu chat | D104: noi serum ban chay nhat dc ko | F104: =IF(E104=1,1,0) | G104: =IF(AND(E104<>"",E104<=5),1,0) | H104: brand/claims-policy#cp-12 | I104: creative/learnings-2023#ct-04 | J104: creative/learnings-2023#ct-06 | K104: brand/voice-guide#vocabulary
A105: V26 | B105: Compliance | C105: Tiếng Anh | D105: Can we say a fragranced product suits sensitive skin? | E105: 3 | F105: =IF(E105=1,1,0) | G105: =IF(AND(E105<>"",E105<=5),1,0) | H105: brand/claims-policy#cp-09 | I105: brand/voice-guide#talking-about-scent | J105: research/insights-line-blueberry#evidence-by-theme-2 | K105: brand/claims-policy#cp-09
A106: V26 | B106: Compliance | C106: Tiếng Việt có dấu | D106: Có được nói sản phẩm có hương liệu phù hợp da nhạy cảm không? | E106: 8 | F106: =IF(E106=1,1,0) | G106: =IF(AND(E106<>"",E106<=5),1,0) | H106: brand/claims-policy#cp-09 | I106: research/insights-line-blueberry#evidence-by-theme-2 | J106: research/insights-P436359#evidence-by-theme-2 | K106: brand/claims-policy#cp-04
A107: V26 | B107: Compliance | C107: Không dấu | D107: Co duoc noi san pham co huong lieu phu hop da nhay cam khong? | F107: =IF(E107=1,1,0) | G107: =IF(AND(E107<>"",E107<=5),1,0) | H107: brand/claims-policy#cp-09 | I107: sop/influencer-brief#product-specific-notes-from-customer-research | J107: research/insights-line-blueberry#evidence-by-theme-2 | K107: sop/ad-claim-review#self-check-checklist
A108: V26 | B108: Compliance | C108: Kiểu chat | D108: sp co mui ma ghi hop da nhay cam dc ko | F108: =IF(E108=1,1,0) | G108: =IF(AND(E108<>"",E108<=5),1,0) | H108: brand/claims-policy#cp-09 | I108: sop/influencer-brief#product-specific-notes-from-customer-research | J108: research/insights-line-blueberry#evidence-by-theme-2 | K108: research/insights-P436359#evidence-by-theme-2
A109: V27 | B109: Compliance | C109: Tiếng Anh | D109: What AHA concentration and pH does FDA recommend? | E109: 1 | F109: =IF(E109=1,1,0) | G109: =IF(AND(E109<>"",E109<=5),1,0) | H109: compliance/fda-aha-labeling#other-recommendations | I109: compliance/fda-aha-labeling#other-recommendations | J109: compliance/fda-aha-labeling#glow-recipe-products-containing-ahas-from-ingredient-lists-i | K109: compliance/fda-aha-labeling#recommended-label-statement-verbatim
A110: V27 | B110: Compliance | C110: Tiếng Việt có dấu | D110: FDA khuyến nghị nồng độ AHA và độ pH bao nhiêu? | E110: 1 | F110: =IF(E110=1,1,0) | G110: =IF(AND(E110<>"",E110<=5),1,0) | H110: compliance/fda-aha-labeling#other-recommendations | I110: compliance/fda-aha-labeling#other-recommendations | J110: brand/claims-policy#cp-04 | K110: compliance/fda-aha-labeling#glow-recipe-products-containing-ahas-from-ingredient-lists-i
A111: V27 | B111: Compliance | C111: Không dấu | D111: FDA khuyen nghi nong do AHA va do pH bao nhieu? | E111: 1 | F111: =IF(E111=1,1,0) | G111: =IF(AND(E111<>"",E111<=5),1,0) | H111: compliance/fda-aha-labeling#other-recommendations | I111: compliance/fda-aha-labeling#other-recommendations | J111: brand/claims-policy#cp-04 | K111: compliance/fda-aha-labeling#glow-recipe-products-containing-ahas-from-ingredient-lists-i
A112: V27 | B112: Compliance | C112: Kiểu chat | D112: fda noi aha bao nhieu % ph bao nhieu | E112: 1 | F112: =IF(E112=1,1,0) | G112: =IF(AND(E112<>"",E112<=5),1,0) | H112: compliance/fda-aha-labeling#other-recommendations | I112: compliance/fda-aha-labeling#other-recommendations | J112: brand/claims-policy#cp-04 | K112: compliance/fda-aha-labeling#glow-recipe-products-containing-ahas-from-ingredient-lists-i
A113: V28 | B113: Compliance | C113: Tiếng Anh | D113: What counts as a serious adverse event under MoCRA? | E113: 2 | F113: =IF(E113=1,1,0) | G113: =IF(AND(E113<>"",E113<=5),1,0) | H113: compliance/fda-mocra-adverse-events#what-counts-as-serious sop/adverse-event-escalation#steps | I113: compliance/fda-mocra-adverse-events#overview | J113: compliance/fda-mocra-adverse-events#what-counts-as-serious | K113: compliance/fda-mocra-adverse-events#reporting-duty
A114: V28 | B114: Compliance | C114: Tiếng Việt có dấu | D114: Theo MoCRA, thế nào là phản ứng phụ nghiêm trọng? | E114: 1 | F114: =IF(E114=1,1,0) | G114: =IF(AND(E114<>"",E114<=5),1,0) | H114: compliance/fda-mocra-adverse-events#what-counts-as-serious sop/adverse-event-escalation#steps | I114: compliance/fda-mocra-adverse-events#what-counts-as-serious | J114: compliance/fda-mocra-adverse-events#relevance-to-this-knowledge-base | K114: compliance/fda-mocra-adverse-events#overview
A115: V28 | B115: Compliance | C115: Không dấu | D115: Theo MoCRA, the nao la phan ung phu nghiem trong? | E115: 3 | F115: =IF(E115=1,1,0) | G115: =IF(AND(E115<>"",E115<=5),1,0) | H115: compliance/fda-mocra-adverse-events#what-counts-as-serious sop/adverse-event-escalation#steps | I115: compliance/fda-mocra-adverse-events#overview | J115: compliance/fda-mocra-adverse-events#relevance-to-this-knowledge-base | K115: compliance/fda-mocra-adverse-events#what-counts-as-serious
A116: V28 | B116: Compliance | C116: Kiểu chat | D116: the nao la phan ung nghiem trong theo mocra | E116: 2 | F116: =IF(E116=1,1,0) | G116: =IF(AND(E116<>"",E116<=5),1,0) | H116: compliance/fda-mocra-adverse-events#what-counts-as-serious sop/adverse-event-escalation#steps | I116: compliance/fda-mocra-adverse-events#overview | J116: compliance/fda-mocra-adverse-events#what-counts-as-serious | K116: compliance/fda-mocra-adverse-events#relevance-to-this-knowledge-base
A117: V29 | B117: Compliance | C117: Tiếng Anh | D117: Do influencers need to disclose in every post or just once? | E117: 1 | F117: =IF(E117=1,1,0) | G117: =IF(AND(E117<>"",E117<=5),1,0) | H117: compliance/ftc-endorsement-guides#when-a-disclosure-is-required brand/claims-policy#cp-10 sop/influencer-brief#mandatory-brief-sections | I117: compliance/ftc-endorsement-guides#when-a-disclosure-is-required | J117: brand/claims-policy#cp-10 | K117: sop/influencer-brief#mandatory-brief-sections
A118: V29 | B118: Compliance | C118: Tiếng Việt có dấu | D118: Influencer phải ghi chú quảng cáo ở mọi bài hay chỉ một lần? | E118: 1 | F118: =IF(E118=1,1,0) | G118: =IF(AND(E118<>"",E118<=5),1,0) | H118: compliance/ftc-endorsement-guides#when-a-disclosure-is-required brand/claims-policy#cp-10 sop/influencer-brief#mandatory-brief-sections | I118: brand/claims-policy#cp-10 | J118: compliance/ftc-endorsement-guides#when-a-disclosure-is-required | K118: brand/claims-policy#overview
A119: V29 | B119: Compliance | C119: Không dấu | D119: Influencer phai ghi chu quang cao o moi bai hay chi mot lan? | E119: 1 | F119: =IF(E119=1,1,0) | G119: =IF(AND(E119<>"",E119<=5),1,0) | H119: compliance/ftc-endorsement-guides#when-a-disclosure-is-required brand/claims-policy#cp-10 sop/influencer-brief#mandatory-brief-sections | I119: sop/influencer-brief#mandatory-brief-sections | J119: brand/claims-policy#cp-10 | K119: compliance/ftc-endorsement-guides#when-a-disclosure-is-required
A120: V29 | B120: Compliance | C120: Kiểu chat | D120: kol co can ghi #ad moi bai ko | E120: 1 | F120: =IF(E120=1,1,0) | G120: =IF(AND(E120<>"",E120<=5),1,0) | H120: compliance/ftc-endorsement-guides#when-a-disclosure-is-required brand/claims-policy#cp-10 sop/influencer-brief#mandatory-brief-sections | I120: sop/influencer-brief#mandatory-brief-sections | J120: brand/claims-policy#cp-10 | K120: creative/learnings-2023#open-questions-and-data-gaps
... A146: V36 | B146: SOP | C146: Tiếng Việt có dấu | D146: CSKH tuyệt đối không được nói gì với khách bị phản ứng da? | E146: 7 | F146: =IF(E146=1,1,0) | G146: =IF(AND(E146<>"",E146<=5),1,0) | H146: sop/adverse-event-escalation#do-not sop/review-response#principles | I146: sop/adverse-event-escalation#trigger | J146: sop/influencer-brief#product-specific-notes-from-customer-research | K146: compliance/fda-mocra-adverse-events#relevance-to-this-knowledge-base
A147: V36 | B147: SOP | C147: Không dấu | D147: CSKH tuyet doi khong duoc noi gi voi khach bi phan ung da? | F147: =IF(E147=1,1,0) | G147: =IF(AND(E147<>"",E147<=5),1,0) | H147: sop/adverse-event-escalation#do-not sop/review-response#principles | I147: sop/influencer-brief#product-specific-notes-from-customer-research | J147: creative/learnings-2023#ct-03 | K147: creative/learnings-2023#ct-04
A148: V36 | B148: SOP | C148: Kiểu chat | D148: cskh ko dc noi gi khi khach bi kich ung | F148: =IF(E148=1,1,0) | G148: =IF(AND(E148<>"",E148<=5),1,0) | H148: sop/adverse-event-escalation#do-not sop/review-response#principles | I148: brand/claims-policy#cp-01 | J148: sop/adverse-event-escalation#trigger | K148: sop/adverse-event-escalation#steps
A149: V37 | B149: SOP | C149: Tiếng Anh | D149: How quickly must we respond to 1-star reviews? | E149: 1 | F149: =IF(E149=1,1,0) | G149: =IF(AND(E149<>"",E149<=5),1,0) | H149: sop/review-response#principles | I149: sop/review-response#principles | J149: research/insights-P475543#evidence-by-theme-2 | K149: sop/review-response#reply-templates
A150: V37 | B150: SOP | C150: Tiếng Việt có dấu | D150: Phải trả lời review 1 sao trong bao lâu? | E150: 1 | F150: =IF(E150=1,1,0) | G150: =IF(AND(E150<>"",E150<=5),1,0) | H150: sop/review-response#principles | I150: sop/review-response#principles | J150: research/insights-line-blueberry#themes | K150: sop/review-response#reply-templates
A151: V37 | B151: SOP | C151: Không dấu | D151: Phai tra loi review 1 sao trong bao lau? | E151: 8 | F151: =IF(E151=1,1,0) | G151: =IF(AND(E151<>"",E151<=5),1,0) | H151: sop/review-response#principles | I151: research/insights-line-blueberry#themes | J151: sop/ad-claim-review#steps | K151: research/insights-P436359#themes
A152: V37 | B152: SOP | C152: Kiểu chat | D152: rep review 1 sao trong bao lau | F152: =IF(E152=1,1,0) | G152: =IF(AND(E152<>"",E152<=5),1,0) | H152: sop/review-response#principles | I152: research/insights-line-papaya#themes | J152: research/insights-line-blueberry#themes | K152: research/insights-P436359#themes
A153: V38 | B153: SOP | C153: Tiếng Anh | D153: How long must a creator use the product before posting? | E153: 1 | F153: =IF(E153=1,1,0) | G153: =IF(AND(E153<>"",E153<=5),1,0) | H153: sop/influencer-brief#mandatory-brief-sections | I153: sop/influencer-brief#mandatory-brief-sections | J153: sop/influencer-brief#steps | K153: compliance/ftc-endorsement-guides#brand-responsibilities
A154: V38 | B154: SOP | C154: Tiếng Việt có dấu | D154: Creator phải dùng sản phẩm bao lâu trước khi đăng bài? | E154: 1 | F154: =IF(E154=1,1,0) | G154: =IF(AND(E154<>"",E154<=5),1,0) | H154: sop/influencer-brief#mandatory-brief-sections | I154: sop/influencer-brief#mandatory-brief-sections | J154: sop/influencer-brief#steps | K154: sop/influencer-brief#when-to-use
A155: V38 | B155: SOP | C155: Không dấu | D155: Creator phai dung san pham bao lau truoc khi dang bai? | E155: 4 | F155: =IF(E155=1,1,0) | G155: =IF(AND(E155<>"",E155<=5),1,0) | H155: sop/influencer-brief#mandatory-brief-sections | I155: sop/influencer-brief#when-to-use | J155: sop/influencer-brief#product-specific-notes-from-customer-research | K155: sop/influencer-brief#steps
A156: V38 | B156: SOP | C156: Kiểu chat | D156: koc xai bao lau moi dc dang | F156: =IF(E156=1,1,0) | G156: =IF(AND(E156<>"",E156<=5),1,0) | H156: sop/influencer-brief#mandatory-brief-sections | I156: sop/influencer-brief#product-specific-notes-from-customer-research | J156: creative/learnings-2023#ct-01 | K156: creative/learnings-2023#ct-02
...

Sheet KB - theo câu
A1: Tìm tài liệu trong kb: hạng của chunk đúng theo từng câu
A2: Xanh = hạng 1, vàng = hạng 2-5, đỏ = ngoài top 5 hoặc không tìm thấy (ô trống).
A4: ID | B4: Nhóm | C4: Câu hỏi (tiếng Việt) | D4: Tiếng Anh | E4: Tiếng Việt có dấu | F4: Không dấu | G4: Kiểu chat | H4: Đáp án mong đợi
A5: V01 | B5: Sản phẩm | C5: Serum Avocado phục hồi hàng rào da giá bao nhiêu? | D5: 1 | E5: 1 | F5: 2 | G5: 5 | H5: product/P470529#overview
A6: V02 | B6: Sản phẩm | C6: Kem mắt Guava có vitamin C không? | D6: 2 | E6: 2 | F6: 1 | G6: 1 | H6: product/P501760
A7: V03 | B7: Sản phẩm | C7: Xịt khoáng Watermelon Glow dung tích bao nhiêu? | D7: 1 | E7: 1 | F7: 2 | G7: 2 | H7: product/P442744#overview
A8: V04 | B8: Sản phẩm | C8: Kem dưỡng Plum Plump có bản mini không? | D8: 1 | E8: 1 | F8: 1 | G8: 6 | H8: product/P500472 product/P479327
A9: V05 | B9: Sản phẩm | C9: Sản phẩm nào là kem chống nắng? | D9: 1 | E9: 1 | F9: 2 | G9: 1 | H9: product/P481989
A10: V06 | B10: Sản phẩm | C10: Sữa rửa mặt Avocado có thành phần gì? | D10: 1 | E10: 2 | F10: 4 | G10: 5 | H10: product/P503634
A11: V07 | B11: Sản phẩm | C11: Watermelon AHA Night Treatment có phải sản phẩm peel không? | D11: 1 | E11: 1 | F11: 1 | G11: 1 | H11: product/P501254 product/P501570
A12: V08 | B12: Insight | C12: Khách thích điều gì nhất ở serum Plum Plump? | D12: 3 | E12: 6 | F12: 6 | H12: research/insights-P462699
A13: V09 | B13: Insight | C13: Theo review, kem mắt retinol có gây kích ứng không? | D13: 1 | E13: 1 | F13: 1 | G13: 2 | H13: research/insights-P447791
A14: V10 | B14: Insight | C14: Đánh giá sữa rửa mặt Blueberry thay đổi thế nào qua các năm? | D14: 1 | G14: 4 | H14: research/insights-P436359#by-year
A15: V11 | B15: Insight | C15: Loại da nào chấm Dew Drops cao nhất? | D15: 1 | E15: 4 | H15: research/insights-P466123#by-skin-type
A16: V12 | B16: Insight | C16: Khách có thấy kem dưỡng Watermelon Pink Juice bị dính không? | D16: 1 | E16: 2 | F16: 5 | G16: 1 | H16: research/insights-P428819
A17: V13 | B17: Insight | C17: Dòng sản phẩm nào có nhiều review nhất? | D17: 5 | H17: research/insights-overview#by-product-line
A18: V14 | B18: Insight | C18: Bao nhiêu phần trăm review là từ người được tặng sản phẩm? | H18: research/insights-overview#overview
A19: V15 | B19: Insight | C19: Sáp tẩy trang Papaya được đánh giá thế nào? | D19: 2 | E19: 1 | F19: 2 | G19: 9 | H19: research/insights-P460516
A20: V16 | B20: Insight | C20: Nhìn chung khách nói gì về dòng Avocado? | D20: 1 | E20: 2 | F20: 2 | G20: 4 | H20: research/insights-line-avocado
A21: V17 | B21: Insight | C21: Theo review, serum Guava có giúp mờ thâm không? | D21: 2 | E21: 1 | F21: 1 | G21: 4 | H21: research/insights-P475543
A22: V18 | B22: Insight | C22: Toner Watermelon có hợp da dầu không? | D22: 1 | E22: 2 | F22: 2 | G22: 1 | H22: research/insights-P458219
A23: V19 | B23: Compliance | C23: Có được nói serum Avocado phục hồi hàng rào bảo vệ da không? | D23: 4 | H23: brand/claims-policy#cp-01
A24: V20 | B24: Compliance | C24: Có được nói serum Guava làm mờ nám không? | D24: 1 | E24: 4 | F24: 4 | G24: 2 | H24: brand/claims-policy#cp-03
A25: V21 | B25: Compliance | C25: Có được gọi kem chống nắng là sunblock không? | D25: 1 | E25: 1 | F25: 1 | G25: 1 | H25: brand/claims-policy#cp-05 compliance/fda-sunscreen-labeling#prohibited-terms
A26: V22 | B26: Compliance | C26: Nội dung về kem chống nắng phải nhắc thoa lại sau bao lâu? | D26: 1 | E26: 1 | F26: 8 | G26: 8 | H26: brand/claims-policy#cp-05 compliance/fda-sunscreen-labeling#water-resistance
A27: V23 | B27: Compliance | C27: Có được dùng review 'hết sạch mụn' của khách trong quảng cáo không? | D27: 1 | E27: 1 | F27: 4 | G27: 3 | H27: brand/claims-policy#cp-07 brand/claims-policy#cp-02 compliance/ftc-health-claims#5-testimonials-and-endorsements
A28: V24 | B28: Compliance | C28: Có được ghi được bác sĩ da liễu khuyên dùng không? | D28: 2 | E28: 2 | F28: 7 | G28: 5 | H28: brand/claims-policy#cp-06
A29: V25 | B29: Compliance | C29: Có được nói đây là serum bán chạy nhất không? | D29: 5 | H29: brand/claims-policy#cp-12
A30: V26 | B30: Compliance | C30: Có được nói sản phẩm có hương liệu phù hợp da nhạy cảm không? | D30: 3 | E30: 8 | H30: brand/claims-policy#cp-09
A31: V27 | B31: Compliance | C31: FDA khuyến nghị nồng độ AHA và độ pH bao nhiêu? | D31: 1 | E31: 1 | F31: 1 | G31: 1 | H31: compliance/fda-aha-labeling#other-recommendations
A32: V28 | B32: Compliance | C32: Theo MoCRA, thế nào là phản ứng phụ nghiêm trọng? | D32: 2 | E32: 1 | F32: 3 | G32: 2 | H32: compliance/fda-mocra-adverse-events#what-counts-as-serious sop/adverse-event-escalation#steps
A33: V29 | B33: Compliance | C33: Influencer phải ghi chú quảng cáo ở mọi bài hay chỉ một lần? | D33: 1 | E33: 1 | F33: 1 | G33: 1 | H33: compliance/ftc-endorsement-guides#when-a-disclosure-is-required brand/claims-policy#cp-10 sop/influencer-brief#mandatory-brief-sections
A34: V30 | B34: Compliance | C34: Có được chỉ mời khách hài lòng để lại review không? | D34: 1 | E34: 1 | F34: 9 | G34: 1 | H34: compliance/ftc-endorsement-guides#reviews brand/claims-policy#cp-07
A35: V31 | B35: Compliance | C35: 'Net impression' trong hướng dẫn FTC nghĩa là gì? | D35: 1 | E35: 1 | F35: 1 | G35: 1 | H35: compliance/ftc-health-claims#3-net-impression
A36: V32 | B36: SOP | C36: Ai duyệt các claim cần Regulatory xem xét? | D36: 1 | E36: 2 | F36: 2 | G36: 3 | H36: sop/ad-claim-review#roles sop/ad-claim-review#steps
A37: V33 | B37: SOP | C37: Quảng cáo trả phí phải được duyệt trước ngày chạy bao lâu? | D37: 1 | E37: 1 | F37: 1 | G37: 5 | H37: sop/ad-claim-review#steps
A38: V34 | B38: SOP | C38: Nếu quảng cáo đang chạy vi phạm luật BLOCK thì làm gì? | D38: 1 | E38: 1 | F38: 1 | G38: 5 | H38: sop/ad-claim-review#steps
A39: V35 | B39: SOP | C39: CSKH cần thu thập thông tin gì khi khách báo bị phản ứng da? | D39: 2 | E39: 5 | F39: 9 | G39: 8 | H39: sop/adverse-event-escalation#steps
A40: V36 | B40: SOP | C40: CSKH tuyệt đối không được nói gì với khách bị phản ứng da? | D40: 4 | E40: 7 | H40: sop/adverse-event-escalation#do-not sop/review-response#principles
A41: V37 | B41: SOP | C41: Phải trả lời review 1 sao trong bao lâu? | D41: 1 | E41: 1 | F41: 8 | H41: sop/review-response#principles
A42: V38 | B42: SOP | C42: Creator phải dùng sản phẩm bao lâu trước khi đăng bài? | D42: 1 | E42: 1 | F42: 4 | H42: sop/influencer-brief#mandatory-brief-sections
A43: V39 | B43: Chính sách | C43: Có giao hàng quốc tế không? | D43: 2 | E43: 1 | F43: 1 | G43: 3 | H43: policy/shipping#what-the-page-does-not-state policy/returns#exclusions
A44: V40 | B44: Chính sách | C44: Phí vận chuyển ban đầu có được hoàn lại không? | D44: 1 | E44: 4 | H44: policy/returns#key-terms
A45: V41 | B45: Chính sách | C45: Khách có được đổi sản phẩm không? | D45: 1 | E45: 1 | H45: policy/returns#not-covered-by-the-policy-text
A46: V42 | B46: Creative | C46: Quảng cáo hướng dẫn chống vón cho kem chống nắng cho kết quả gì? | D46: 1 | E46: 2 | F46: 9 | H46: creative/learnings-2023#ct-03
A47: V43 | B47: Creative | C47: UGC hay ảnh studio hiệu quả hơn? | D47: 2 | E47: 2 | F47: 2 | G47: 2 | H47: creative/learnings-2023#cross-test-learnings
A48: V44 | B48: Creative | C48: Nên test gì tiếp theo cho serum Guava? | D48: 1 | E48: 1 | F48: 1 | G48: 5 | H48: creative/learnings-2023#recommended-next-tests creative/learnings-2023#open-questions-and-data-gaps
A49: V45 | B49: Creative | C49: Khi nào một bài test được coi là thắng? | H49: creative/learnings-2023#how-to-read-this
A50: V46 | B50: Brand | C50: Được dùng những emoji nào? | D50: 1 | E50: 1 | F50: 1 | G50: 1 | H50: brand/voice-guide#emoji-palette
A51: V47 | B51: Brand | C51: Tiêu đề email nên dài bao nhiêu? | D51: 1 | E51: 1 | F51: 10 | G51: 1 | H51: brand/voice-guide#channel-formats
A52: V48 | B52: Brand | C52: Những từ nào nên tránh khi viết nội dung thương hiệu? | D52: 1 | E52: 1 | F52: 4 | H52: brand/voice-guide#vocabulary
A53: V49 | B53: Brand | C53: Tagline của Glow Recipe là gì? | D53: 1 | E53: 1 | F53: 1 | G53: 1 | H53: brand/brand-overview#positioning
A54: V50 | B54: Brand | C54: Creative brief cần những phần nào? | D54: 1 | E54: 1 | F54: 1 | G54: 1 | H54: creative/brief-template#overview
A55: V51 | B55: Khoảng trống dữ liệu | C55: Kem chống nắng có phổ rộng (broad spectrum) không? | D55: 1 | E55: 1 | F55: 1 | G55: 1 | H55: brand/claims-policy#cp-05 compliance/fda-sunscreen-labeling#relevance compliance/fda-sunscreen-labeling#other-points sop/ad-claim-review#claims-register-status
A56: V52 | B56: Khoảng trống dữ liệu | C56: Có nghiên cứu lâm sàng nào cho sản phẩm không? | D56: 1 | E56: 1 | F56: 2 | G56: 1 | H56: compliance/ftc-health-claims#practical-implications brand/claims-policy#cp-06 sop/ad-claim-review#claims-register-status brand/brand-overview#not-in-the-knowledge-base
A57: V53 | B57: Khoảng trống dữ liệu | C57: Khách nghĩ gì về kem dưỡng thể Pink Dream? | D57: 1 | E57: 1 | F57: 1 | G57: 1 | H57: product/P469211 research/insights-overview#known-gaps

Sheet Review
A1: Tìm review có bộ lọc: precision@5
A2: Precision@5 = số review trong top 5 khớp từ khoá nhãn / 5. Vi phạm = số kết quả sai bộ lọc (phải bằng 0).
A4: ID | B4: Biến thể | C4: Câu hỏi | D4: Bộ lọc | E4: Từ khoá nhãn (regex) | F4: Số kết quả | G4: Precision@5 | H4: Vi phạm bộ lọc | I4: Review không liên quan
A5: RV01 | B5: Tiếng Anh | C5: pilling under makeup | D5: {"product_ids": "P481989", "rating_lte": 2} | E5: pill|ball(s|ing)? up|flak|peel | F5: 5 | G5: 1 | H5: 0
A6: RV01 | B6: Tiếng Việt có dấu | C6: bị vón khi trang điểm | D6: {"product_ids": "P481989", "rating_lte": 2} | E6: pill|ball(s|ing)? up|flak|peel | F6: 5 | G6: 0.8 | H6: 0 | I6: review/P481989-22246
A7: RV01 | B7: Không dấu | C7: bi von khi trang diem | D7: {"product_ids": "P481989", "rating_lte": 2} | E7: pill|ball(s|ing)? up|flak|peel | F7: 5 | G7: 0.8 | H7: 0 | I7: review/P481989-22129
A8: RV02 | B8: Tiếng Anh | C8: leaves a white cast on darker skin | D8: {"product_ids": "P481989"} | E8: white cast|cast|ashy|gr[ae]y|whitish | F8: 5 | G8: 1 | H8: 0
A9: RV02 | B9: Tiếng Việt có dấu | C9: để lại vệt trắng trên da ngăm | D9: {"product_ids": "P481989"} | E9: white cast|cast|ashy|gr[ae]y|whitish | F9: 5 | G9: 1 | H9: 0
A10: RV02 | B10: Không dấu | C10: de lai vet trang tren da ngam | D10: {"product_ids": "P481989"} | E10: white cast|cast|ashy|gr[ae]y|whitish | F10: 5 | G10: 0.6 | H10: 0 | I10: review/P481989-22084 review/P481989-22290
A11: RV03 | B11: Tiếng Anh | C11: it broke me out | D11: {"product_ids": "P482535"} | E11: break ?out|broke|pimple|acne|purg|zit|bump | F11: 5 | G11: 1 | H11: 0
A12: RV03 | B12: Tiếng Việt có dấu | C12: dùng xong bị nổi mụn | D12: {"product_ids": "P482535"} | E12: break ?out|broke|pimple|acne|purg|zit|bump | F12: 5 | G12: 1 | H12: 0
A13: RV03 | B13: Không dấu | C13: dung xong bi noi mun | D13: {"product_ids": "P482535"} | E13: break ?out|broke|pimple|acne|purg|zit|bump | F13: 5 | G13: 0.6 | H13: 0 | I13: review/P482535-23329 review/P482535-23216
A14: RV04 | B14: Tiếng Anh | C14: smells amazing | D14: {"product_ids": "P428819", "rating_gte": 4} | E14: smell|scent|fragran|aroma | F14: 5 | G14: 1 | H14: 0
A15: RV04 | B15: Tiếng Việt có dấu | C15: mùi thơm rất dễ chịu | D15: {"product_ids": "P428819", "rating_gte": 4} | E15: smell|scent|fragran|aroma | F15: 5 | G15: 0.8 | H15: 0 | I15: review/P428819-00618
A16: RV04 | B16: Không dấu | C16: mui thom rat de chiu | D16: {"product_ids": "P428819", "rating_gte": 4} | E16: smell|scent|fragran|aroma | F16: 5 | G16: 0.4 | H16: 0 | I16: review/P428819-01857 review/P428819-00251 review/P428819-00185
A17: RV05 | B17: Tiếng Anh | C17: feels too sticky | D17: {"product_ids": "P466123", "rating_lte": 2} | E17: stick|tack|gummy|residue | F17: 5 | G17: 1 | H17: 0
A18: RV05 | B18: Tiếng Việt có dấu | C18: cảm giác dính nhớp | D18: {"product_ids": "P466123", "rating_lte": 2} | E18: stick|tack|gummy|residue | F18: 5 | G18: 1 | H18: 0
A19: RV05 | B19: Không dấu | C19: cam giac dinh nhop | D19: {"product_ids": "P466123", "rating_lte": 2} | E19: stick|tack|gummy|residue | F19: 5 | G19: 0.8 | H19: 0 | I19: review/P466123-15848
A20: RV06 | B20: Tiếng Anh | C20: burning sensation on my face | D20: {"product_ids": "P436359"} | E20: burn|sting|tingl|irritat|hot | F20: 5 | G20: 1 | H20: 0
A21: RV06 | B21: Tiếng Việt có dấu | C21: bị rát, nóng mặt | D21: {"product_ids": "P436359"} | E21: burn|sting|tingl|irritat|hot | F21: 5 | G21: 0.6 | H21: 0 | I21: review/P436359-02644 review/P436359-02504
A22: RV06 | B22: Không dấu | C22: bi rat, nong mat | D22: {"product_ids": "P436359"} | E22: burn|sting|tingl|irritat|hot | F22: 5 | G22: 0.4 | H22: 0 | I22: review/P436359-02484 review/P436359-02634 review/P436359-02402
A23: RV07 | B23: Tiếng Anh | C23: very hydrating and plumping | D23: {"product_ids": "P479327", "rating_gte": 4} | E23: hydrat|plump|moistur|bouncy|dewy|juicy | F23: 5 | G23: 1 | H23: 0
A24: RV07 | B24: Tiếng Việt có dấu | C24: cấp ẩm tốt, da căng mọng | D24: {"product_ids": "P479327", "rating_gte": 4} | E24: hydrat|plump|moistur|bouncy|dewy|juicy | F24: 5 | G24: 0.8 | H24: 0 | I24: review/P479327-19795
A25: RV07 | B25: Không dấu | C25: cap am tot, da cang mong | D25: {"product_ids": "P479327", "rating_gte": 4} | E25: hydrat|plump|moistur|bouncy|dewy|juicy | F25: 5 | G25: 0.6 | H25: 0 | I25: review/P479327-19795 review/P479327-21030
A26: RV08 | B26: Tiếng Anh | C26: removes makeup easily | D26: {"product_ids": "P460516"} | E26: makeup|make up|mascara|remov|melt|sunscreen | F26: 5 | G26: 1 | H26: 0
A27: RV08 | B27: Tiếng Việt có dấu | C27: tẩy trang sạch dễ dàng | D27: {"product_ids": "P460516"} | E27: makeup|make up|mascara|remov|melt|sunscreen | F27: 5 | G27: 1 | H27: 0
A28: RV08 | B28: Không dấu | C28: tay trang sach de dang | D28: {"product_ids": "P460516"} | E28: makeup|make up|mascara|remov|melt|sunscreen | F28: 5 | G28: 0.4 | H28: 0 | I28: review/P460516-11803 review/P460516-12061 review/P460516-11507
A29: RV09 | B29: Tiếng Anh | C29: my dark spots faded | D29: {"product_ids": "P475543"} | E29: spot|dark|hyperpig|scar|discolor|mark|fad | F29: 5 | G29: 1 | H29: 0
A30: RV09 | B30: Tiếng Việt có dấu | C30: vết thâm mờ đi | D30: {"product_ids": "P475543"} | E30: spot|dark|hyperpig|scar|discolor|mark|fad | F30: 5 | G30: 1 | H30: 0
A31: RV09 | B31: Không dấu | C31: vet tham mo di | D31: {"product_ids": "P475543"} | E31: spot|dark|hyperpig|scar|discolor|mark|fad | F31: 5 | G31: 0.2 | H31: 0 | I31: review/P475543-19295 review/P475543-19251 review/P475543-19309 review/P475543-19363
A32: RV10 | B32: Tiếng Anh | C32: reduced fine lines under my eyes | D32: {"product_ids": "P447791"} | E32: line|wrinkle|crow|crease | F32: 5 | G32: 1 | H32: 0
A33: RV10 | B33: Tiếng Việt có dấu | C33: giảm nếp nhăn vùng mắt | D33: {"product_ids": "P447791"} | E33: line|wrinkle|crow|crease | F33: 5 | G33: 0.8 | H33: 0 | I33: review/P447791-05886
A34: RV10 | B34: Không dấu | C34: giam nep nhan vung mat | D34: {"product_ids": "P447791"} | E34: line|wrinkle|crow|crease | F34: 5 | G34: 0.2 | H34: 0 | I34: review/P447791-05886 review/P447791-05644 review/P447791-04744 review/P447791-06313
A35: RV11 | B35: Tiếng Anh | C35: my pores look smaller | D35: {"product_ids": "P458219", "rating_gte": 4} | E35: pore | F35: 5 | G35: 1 | H35: 0
A36: RV11 | B36: Tiếng Việt có dấu | C36: lỗ chân lông nhỏ lại | D36: {"product_ids": "P458219", "rating_gte": 4} | E36: pore | F36: 5 | G36: 1 | H36: 0
A37: RV11 | B37: Không dấu | C37: lo chan long nho lai | D37: {"product_ids": "P458219", "rating_gte": 4} | E37: pore | F37: 5 | G37: 0.2 | H37: 0 | I37: review/P458219-10036 review/P458219-08904 review/P458219-08559 review/P458219-09978
A38: RV12 | B38: Tiếng Anh | C38: calmed my redness | D38: {"product_ids": "P470529"} | E38: red|calm|sooth|rosacea|irritat | F38: 5 | G38: 1 | H38: 0
A39: RV12 | B39: Tiếng Việt có dấu | C39: làm dịu da ửng đỏ | D39: {"product_ids": "P470529"} | E39: red|calm|sooth|rosacea|irritat | F39: 5 | G39: 1 | H39: 0
A40: RV12 | B40: Không dấu | C40: lam diu da ung do | D40: {"product_ids": "P470529"} | E40: red|calm|sooth|rosacea|irritat | F40: 5 | G40: 0.8 | H40: 0 | I40: review/P470529-17453
A41: RV13 | B41: Tiếng Anh | C41: too expensive for such a small bottle | D41: {"product_ids": "P462699"} | E41: price|expensive|pricey|worth|money|cost|\$|small|tiny|size | F41: 5 | G41: 0.8 | H41: 0 | I41: review/P462699-13897
A42: RV13 | B42: Tiếng Việt có dấu | C42: quá đắt so với dung tích | D42: {"product_ids": "P462699"} | E42: price|expensive|pricey|worth|money|cost|\$|small|tiny|size | F42: 5 | G42: 1 | H42: 0
A43: RV13 | B43: Không dấu | C43: qua dat so voi dung tich | D43: {"product_ids": "P462699"} | E43: price|expensive|pricey|worth|money|cost|\$|small|tiny|size | F43: 5 | G43: 0 | H43: 0 | I43: review/P462699-14177 review/P462699-13857 review/P462699-14089 review/P462699-12925 review/P462699-12576
A44: RV14 | B44: Tiếng Anh | C44: great for my dry skin | D44: {"product_ids": "P466123", "skin_type": "dry"} | E44: dry|hydrat|moistur|flak | F44: 5 | G44: 1 | H44: 0
A45: RV14 | B45: Tiếng Việt có dấu | C45: rất hợp với da khô của tôi | D45: {"product_ids": "P466123", "skin_type": "dry"} | E45: dry|hydrat|moistur|flak | F45: 5 | G45: 1 | H45: 0
A46: RV14 | B46: Không dấu | C46: rat hop voi da kho cua toi | D46: {"product_ids": "P466123", "skin_type": "dry"} | E46: dry|hydrat|moistur|flak | F46: 5 | G46: 0.8 | H46: 0 | I46: review/P466123-14315
A47: RV15 | B47: Tiếng Anh | C47: stings my eyes | D47: {"product_ids": "P501760"} | E47: sting|burn|irritat|water|tear|eyes? (were|was)? ?(red|itch) | F47: 5 | G47: 1 | H47: 0
A48: RV15 | B48: Tiếng Việt có dấu | C48: bị cay mắt | D48: {"product_ids": "P501760"} | E48: sting|burn|irritat|water|tear|eyes? (were|was)? ?(red|itch) | F48: 5 | G48: 0.4 | H48: 0 | I48: review/P501760-25000 review/P501760-24753 review/P501760-24901
A49: RV15 | B49: Không dấu | C49: bi cay mat | D49: {"product_ids": "P501760"} | E49: sting|burn|irritat|water|tear|eyes? (were|was)? ?(red|itch) | F49: 5 | G49: 0 | H49: 0 | I49: review/P501760-24383 review/P501760-25002 review/P501760-24960 review/P501760-25018 review/P501760-24753

Sheet Ngoài phạm vi
A1: Nhận biết câu hỏi ngoài phạm vi bằng điểm tương đồng
A2: Đổi ngưỡng ở ô C4 để xem bao nhiêu câu ngoài phạm vi bị loại (điểm < ngưỡng).
A4: Ngưỡng điểm tương đồng (cosine) | C4: 0.768 | D4: Ngưỡng tốt nhất tìm được trên lần chạy này (giữ 100% câu hợp lệ).
A5: Tỉ lệ câu ngoài phạm vi bị loại | C5: =COUNTIF(F8:F31,"Có")/COUNTA(F8:F31)
A7: ID | B7: Ngôn ngữ | C7: Lý do ngoài phạm vi | D7: Câu hỏi | E7: Điểm (cosine) | F7: Bị loại? | G7: Chunk gần nhất
A8: N01 | B8: Tiếng Anh | C8: excluded product (lip balm) | D8: How much is the Glow Lip Pop lip balm? | E8: 0.847 | F8: =IF(E8<$C$4,"Có","Không") | G8: catalog/overview#catalog-summary
A9: N08 | B9: Tiếng Việt | C9: data not in KB (retail) | D9: Glow Recipe có cửa hàng ở Việt Nam không? | E9: 0.821 | F9: =IF(E9<$C$4,"Có","Không") | G9: brand/brand-overview#positioning
A10: N01 | B10: Tiếng Việt | C10: excluded product (lip balm) | D10: Son dưỡng Glow Lip Pop giá bao nhiêu? | E10: 0.82 | F10: =IF(E10<$C$4,"Có","Không") | G10: catalog/overview#catalog-summary
A11: N10 | B11: Tiếng Anh | C11: competitor product | D11: How much does the Rare Beauty liquid blush cost? | E11: 0.818 | F11: =IF(E11<$C$4,"Có","Không") | G11: policy/shipping#useful-for-copy
A12: N08 | B12: Tiếng Anh | C12: data not in KB (retail) | D12: Does Glow Recipe have physical stores in Vietnam? | E12: 0.817 | F12: =IF(E12<$C$4,"Có","Không") | G12: brand/brand-overview#positioning
A13: N02 | B13: Tiếng Anh | C13: excluded product (kit) | D13: What is inside the Fruit Babies Bestsellers Kit? | E13: 0.81 | F13: =IF(E13<$C$4,"Có","Không") | G13: catalog/overview#catalog-summary
A14: N09 | B14: Tiếng Anh | C14: category not sold | D14: Recommend a perfume for men | E14: 0.808 | F14: =IF(E14<$C$4,"Có","Không") | G14: brand/voice-guide#talking-about-scent
A15: N02 | B15: Tiếng Việt | C15: excluded product (kit) | D15: Bộ Fruit Babies Bestsellers Kit gồm những gì? | E15: 0.801 | F15: =IF(E15<$C$4,"Có","Không") | G15: catalog/overview#catalog-summary
A16: N04 | B16: Tiếng Anh | C16: category not sold | D16: Do you sell a hair shampoo? | E16: 0.801 | F16: =IF(E16<$C$4,"Có","Không") | G16: sop/influencer-brief#product-specific-notes-from-customer-research
A17: N09 | B17: Tiếng Việt | C17: category not sold | D17: Gợi ý nước hoa cho nam | E17: 0.798 | F17: =IF(E17<$C$4,"Có","Không") | G17: research/insights-line-papaya#themes
A18: N06 | B18: Tiếng Anh | C18: off-topic (account support) | D18: How do I reset my account password? | E18: 0.795 | F18: =IF(E18<$C$4,"Có","Không") | G18: sop/adverse-event-escalation#customer-script
A19: N03 | B19: Tiếng Anh | C19: other company | D19: Who is the CEO of Sephora? | E19: 0.791 | F19: =IF(E19<$C$4,"Có","Không") | G19: brand/claims-policy#cp-09
... A31: N05 | B31: Tiếng Việt | C31: off-topic | D31: Thời tiết Hà Nội ngày mai thế nào? | E31: 0.701 | F31: =IF(E31<$C$4,"Có","Không") | G31: research/insights-P462699#evidence-by-theme-1
A33: Tham chiếu: điểm của câu hỏi hợp lệ (phần A, tiếng Anh + tiếng Việt)
A34: Thấp nhất | C34: 0.768
A35: Trung vị | C35: 0.838
A36: Cao nhất | C36: 0.909
